MANIFEST.in
requirements.txt
setup.py
src/NcclientLibrary/NcclientKeywords.py
src/NcclientLibrary/__init__.py
src/NcclientLibrary/version.py
src/robotframework_ncclient.egg-info/PKG-INFO
src/robotframework_ncclient.egg-info/SOURCES.txt
src/robotframework_ncclient.egg-info/dependency_links.txt
src/robotframework_ncclient.egg-info/requires.txt
src/robotframework_ncclient.egg-info/top_level.txt