Metadata-Version: 1.1
Name: robotframework-ncclient
Version: 0.1.6
Summary: Robot Framework keyword library wrapper around ncclient
Home-page: https://github.com/vkosuri/robotframework-ncclient
Author: Mallikarjunarao Kosuri
Author-email: venkatamallikarjunarao.kosuri@adtran.com
License: Public Domain
Keywords: robotframework test automation NETCONF client
Platform: any
Classifier: Development Status :: 5 - Production/Stable
Classifier: License :: Public Domain
Classifier: Operating System :: OS Independent
Classifier: Programming Language :: Python
Classifier: Topic :: Software Development :: Testing
